{"2017-3":[{"title":"Hello World","date":"2017-03-13T13:48:00.351Z","link":"/2017/03/13/hello-world/"},{"title":"C++ 关于cin() 和 getline();","date":"2017-03-13T13:54:16.615Z","link":"/2017/03/13/c++_cin/"},{"title":"C++学习随笔  setw( n )","date":"2017-03-13T13:54:16.643Z","link":"/2017/03/13/c++learning/"},{"title":"用Github搭建Hexo博客","date":"2017-03-13T13:54:16.646Z","link":"/2017/03/13/create-hexo/"},{"title":"免费看 VIP 电影/电视剧","date":"2017-03-13T13:54:16.648Z","link":"/2017/03/13/free-watch-movies/"},{"title":"VIM","date":"2017-03-13T14:18:56.436Z","link":"/2017/03/13/vim/"},{"title":"GIT","date":"2017-03-13T14:19:15.908Z","link":"/2017/03/13/Git/"},{"title":"First Hexo","date":"2017-03-13T14:22:28.698Z","link":"/2017/03/13/white-black/"},{"title":"Error in Hexo Learning","date":"2017-03-13T14:45:04.287Z","link":"/2017/03/13/Errors_hexo_Learning/"},{"title":"test of Markdown syntax","date":"2017-03-14T11:48:26.596Z","link":"/2017/03/14/test/"},{"title":"c language point","date":"2017-03-22T12:50:59.599Z","link":"/2017/03/22/c_record/"},{"title":"add user","date":"2017-03-25T16:03:04.919Z","link":"/2017/03/26/ubuntu/"}],"2017-4":[{"title":"民谣真的变味了吗","date":"2017-04-05T16:18:25.141Z","link":"/2017/04/06/minyao/"},{"title":"usage of string","date":"2017-04-11T11:45:04.841Z","link":"/2017/04/11/string/"}],"2017-5":[{"title":"AutoLisp","date":"2017-05-02T14:43:56.473Z","link":"/2017/05/02/AutoLisp/"},{"title":"","date":"2017-05-06T16:00:00.000Z","link":"/2017/05/07/test1/"},{"title":"shell 编程学习","date":"2017-05-08T13:17:51.305Z","link":"/2017/05/08/shell/"},{"title":"像计算机科学家一样的思考","date":"2017-05-12T15:14:37.445Z","link":"/2017/05/12/c++programming/"}],"2017-6":[{"title":"Linux命令下打包压缩文件","date":"2017-06-18T16:00:22.925Z","link":"/2017/06/19/linux_tar/"}],"2017-7":[{"title":"不用安装各种软件，而且可以翻墙的工具","date":"2017-07-05T08:18:46.502Z","link":"/2017/07/05/uzerme/"},{"title":"关于excel文件的密码破解","date":"2017-07-06T07:44:41.525Z","link":"/2017/07/06/broken_passwd_excel/"},{"title":"Ubuntu 中 HISTSIZE 、 HISTFILESIZE 、HISTTIMEFORMAT 的设置","date":"2017-07-16T04:32:34.339Z","link":"/2017/07/16/histsize_bashrc/"}],"2017-8":[{"title":"shell script 的执行方式和区别","date":"2017-08-05T08:11:11.639Z","link":"/2017/08/05/shell_perform/"}],"2017-9":[{"title":"Linux 中的 进程管理函数 forl()","date":"2017-09-05T16:04:59.186Z","link":"/2017/09/06/fork/"},{"title":"统计统计文件的字符数","date":"2017-09-07T14:56:15.771Z","link":"/2017/09/07/countcharacter/"}],"2018-1":[{"title":"","date":"2018-01-18T15:47:04.554Z","link":"/2018/01/18/python/"}]}